{
  "type": "FeatureCollection", 
  "features": [
    {
      "geometry": {
        "type": "Polygon", 
        "coordinates": [
          [
            [
              10.709, 
              55.345
            ], 
            [
              10.709, 
              55.363
            ], 
            [
              10.741, 
              55.363
            ], 
            [
              10.741, 
              55.345
            ], 
            [
              10.709, 
              55.345
            ]
          ]
        ]
      }, 
      "type": "Feature", 
      "properties": {
        "lang": "DAN", 
        "woeid": 552144, 
        "name": "Avnslev", 
        "adjacent_woeid": [
          551940, 
          554958, 
          555807, 
          556564, 
          556978, 
          29306122, 
          29306530
        ], 
        "ne_latitude": 55.363, 
        "provider": "geoplanet 7.6.0", 
        "ne_longitude": 10.741, 
        "longitude": 10.725, 
        "placetype": "Town", 
        "iso": "DK", 
        "date_indexed": "2010-12-02T16:13:02Z", 
        "parent_woeid": 12582684, 
        "latitude": 55.354, 
        "sw_longitude": 10.709, 
        "fullname": "Avnslev, Syddanmark, Nyborg, Denmark", 
        "alias_DAN_V": [
          "Aunslev"
        ], 
        "sw_latitude": 55.345
      }, 
      "id": 552144
    }
  ]
}