{
  "type": "FeatureCollection", 
  "features": [
    {
      "geometry": {
        "type": "Polygon", 
        "coordinates": [
          [
            [
              175.457, 
              -36.794
            ], 
            [
              175.457, 
              -36.692
            ], 
            [
              175.553, 
              -36.692
            ], 
            [
              175.553, 
              -36.794
            ], 
            [
              175.457, 
              -36.794
            ]
          ]
        ]
      }, 
      "type": "Feature", 
      "properties": {
        "lang": "ENG", 
        "woeid": 2348383, 
        "name": "Coromandel", 
        "adjacent_woeid": [
          2348008, 
          2348370, 
          2349036, 
          2350857, 
          2350884, 
          2351365, 
          2351416, 
          28644244, 
          28644245, 
          28645555
        ], 
        "ne_latitude": -36.692, 
        "provider": "geoplanet 7.6.0", 
        "ne_longitude": 175.553, 
        "longitude": 175.503, 
        "placetype": "Town", 
        "iso": "NZ", 
        "date_indexed": "2010-12-02T17:02:39Z", 
        "parent_woeid": 55875910, 
        "latitude": -36.754, 
        "sw_longitude": 175.457, 
        "fullname": "Coromandel, Waikato, Thames Coromandel District, New Zealand", 
        "sw_latitude": -36.794
      }, 
      "id": 2348383
    }
  ]
}