{
  "type": "FeatureCollection", 
  "features": [
    {
      "geometry": {
        "type": "Polygon", 
        "coordinates": [
          [
            [
              10.242, 
              47.718
            ], 
            [
              10.242, 
              47.733
            ], 
            [
              10.262, 
              47.733
            ], 
            [
              10.262, 
              47.718
            ], 
            [
              10.242, 
              47.718
            ]
          ]
        ]
      }, 
      "type": "Feature", 
      "properties": {
        "lang": "GER", 
        "woeid": 648501, 
        "name": "Ermengerst", 
        "adjacent_woeid": [
          673827, 
          680523, 
          701406, 
          23412184, 
          29347422, 
          29347649, 
          29347657
        ], 
        "ne_latitude": 47.733, 
        "provider": "geoplanet 7.6.0", 
        "ne_longitude": 10.262, 
        "longitude": 10.253, 
        "placetype": "Town", 
        "iso": "DE", 
        "date_indexed": "2010-12-02T09:42:31Z", 
        "parent_woeid": 12635030, 
        "latitude": 47.727, 
        "sw_longitude": 10.242, 
        "fullname": "Ermengerst, Bavaria, Oberallg\u00e4u, Germany", 
        "sw_latitude": 47.718
      }, 
      "id": 648501
    }
  ]
}