{
  "type": "FeatureCollection", 
  "features": [
    {
      "geometry": {
        "type": "Polygon", 
        "coordinates": [
          [
            [
              -5.460, 
              42.880
            ], 
            [
              -5.460, 
              42.889
            ], 
            [
              -5.447, 
              42.889
            ], 
            [
              -5.447, 
              42.880
            ], 
            [
              -5.460, 
              42.880
            ]
          ]
        ]
      }, 
      "type": "Feature", 
      "properties": {
        "lang": "SPA", 
        "woeid": 758098, 
        "name": "Correcillas", 
        "adjacent_woeid": [
          753329, 
          772124, 
          776657, 
          776676, 
          777839, 
          29371968
        ], 
        "ne_latitude": 42.889, 
        "provider": "geoplanet 7.6.0", 
        "ne_longitude": -5.447, 
        "longitude": -5.454, 
        "placetype": "Town", 
        "iso": "ES", 
        "date_indexed": "2010-12-02T17:09:34Z", 
        "parent_woeid": 12691913, 
        "latitude": 42.885, 
        "sw_longitude": -5.460, 
        "fullname": "Correcillas, Castille and Leon, Leon, Spain", 
        "sw_latitude": 42.880
      }, 
      "id": 758098
    }
  ]
}