{
  "type": "FeatureCollection", 
  "features": [
    {
      "type": "Feature", 
      "properties": {
        "lang": "SWE", 
        "adjacent_woeid": [
          886738
        ], 
        "alias_SWE_V": [
          "Norra Vares"
        ], 
        "name": "Norra Vare", 
        "parent_woeid": 12587315, 
        "provider": "geoplanet 7.6.0", 
        "placetype": "Town", 
        "iso": "SE", 
        "woeid": 899848, 
        "date_indexed": "2010-12-02T16:44:42Z"
      }, 
      "id": 899848
    }
  ]
}