{
  "type": "FeatureCollection", 
  "features": [
    {
      "geometry": {
        "type": "Polygon", 
        "coordinates": [
          [
            [
              71.720, 
              26.819
            ], 
            [
              71.720, 
              26.838
            ], 
            [
              71.740, 
              26.838
            ], 
            [
              71.740, 
              26.819
            ], 
            [
              71.720, 
              26.819
            ]
          ]
        ]
      }, 
      "type": "Feature", 
      "properties": {
        "lang": "ENG", 
        "woeid": 29068294, 
        "name": "Modardi", 
        "adjacent_woeid": [
          2287350, 
          2291084, 
          29068295, 
          29068296, 
          29073324
        ], 
        "ne_latitude": 26.838, 
        "provider": "geoplanet 7.6.0", 
        "ne_longitude": 71.740, 
        "longitude": 71.730, 
        "placetype": "Town", 
        "iso": "IN", 
        "date_indexed": "2010-12-02T09:05:53Z", 
        "parent_woeid": 12586663, 
        "latitude": 26.828, 
        "sw_longitude": 71.720, 
        "fullname": "Modardi, Rajasthan, Jaisalmer, India", 
        "sw_latitude": 26.819
      }, 
      "id": 29068294
    }
  ]
}