{
  "type": "FeatureCollection", 
  "features": [
    {
      "geometry": {
        "type": "Polygon", 
        "coordinates": [
          [
            [
              -85.362, 
              42.327
            ], 
            [
              -85.362, 
              42.344
            ], 
            [
              -85.337, 
              42.344
            ], 
            [
              -85.337, 
              42.327
            ], 
            [
              -85.362, 
              42.327
            ]
          ]
        ]
      }, 
      "type": "Feature", 
      "properties": {
        "lang": "ENG", 
        "woeid": 2357370, 
        "name": "Augusta", 
        "adjacent_woeid": [
          2360052, 
          2361182, 
          2408449, 
          2415574, 
          2420707, 
          2425094, 
          2480819, 
          2498313, 
          28744028, 
          28744247
        ], 
        "ne_latitude": 42.344, 
        "provider": "geoplanet 7.6.0", 
        "ne_longitude": -85.337, 
        "longitude": -85.351, 
        "placetype": "Town", 
        "iso": "US", 
        "date_indexed": "2010-12-02T18:36:11Z", 
        "parent_woeid": 12588752, 
        "latitude": 42.335, 
        "sw_longitude": -85.362, 
        "fullname": "Augusta, Michigan, Kalamazoo, United States", 
        "sw_latitude": 42.327
      }, 
      "id": 2357370
    }
  ]
}