{
  "type": "FeatureCollection", 
  "features": [
    {
      "geometry": {
        "type": "Polygon", 
        "coordinates": [
          [
            [
              10.849, 
              50.907
            ], 
            [
              10.849, 
              50.948
            ], 
            [
              10.878, 
              50.948
            ], 
            [
              10.878, 
              50.907
            ], 
            [
              10.849, 
              50.907
            ]
          ]
        ]
      }, 
      "type": "Feature", 
      "properties": {
        "lang": "GER", 
        "woeid": 655165, 
        "name": "Gro\u00dfrettbach", 
        "adjacent_woeid": [
          635317, 
          643227, 
          651456, 
          653720, 
          667109, 
          703867
        ], 
        "alias_GER_S": [
          "Grossrettbach"
        ], 
        "ne_latitude": 50.948, 
        "provider": "geoplanet 7.6.0", 
        "ne_longitude": 10.878, 
        "longitude": 10.862, 
        "placetype": "Town", 
        "iso": "DE", 
        "date_indexed": "2010-12-02T09:43:04Z", 
        "parent_woeid": 12625004, 
        "latitude": 50.925, 
        "sw_longitude": 10.849, 
        "fullname": "Gro\u00dfrettbach, Thuringia, Landkreis Gotha, Germany", 
        "sw_latitude": 50.907
      }, 
      "id": 655165
    }
  ]
}