{
  "type": "FeatureCollection", 
  "features": [
    {
      "geometry": {
        "type": "Polygon", 
        "coordinates": [
          [
            [
              12.879, 
              46.682
            ], 
            [
              12.879, 
              46.700
            ], 
            [
              12.906, 
              46.700
            ], 
            [
              12.906, 
              46.682
            ], 
            [
              12.879, 
              46.682
            ]
          ]
        ]
      }, 
      "type": "Feature", 
      "properties": {
        "lang": "GER", 
        "woeid": 539756, 
        "name": "Kornat", 
        "adjacent_woeid": [
          539421, 
          539952
        ], 
        "ne_latitude": 46.700, 
        "provider": "geoplanet 7.6.0", 
        "ne_longitude": 12.906, 
        "longitude": 12.893, 
        "placetype": "Town", 
        "iso": "AT", 
        "date_indexed": "2010-12-02T16:33:49Z", 
        "parent_woeid": 12673568, 
        "latitude": 46.691, 
        "sw_longitude": 12.879, 
        "fullname": "Kornat, Carinthia, Hermagor, Austria", 
        "sw_latitude": 46.682
      }, 
      "id": 539756
    }
  ]
}