{
  "type": "FeatureCollection", 
  "features": [
    {
      "type": "Feature", 
      "properties": {
        "lang": "ENG", 
        "alias_ENG_V": [
          "Kettin"
        ], 
        "name": "Keptin", 
        "adjacent_woeid": [
          2113581, 
          2043231, 
          2012927, 
          2060480, 
          2011905, 
          2078046, 
          2004297, 
          2043232
        ], 
        "parent_woeid": 12597630, 
        "provider": "geoplanet 7.6.0", 
        "placetype": "Town", 
        "iso": "RU", 
        "woeid": 2018565, 
        "date_indexed": "2010-12-02T16:09:16Z"
      }, 
      "id": 2018565
    }
  ]
}