{
  "type": "FeatureCollection", 
  "features": [
    {
      "geometry": {
        "type": "Polygon", 
        "coordinates": [
          [
            [
              20.296, 
              49.698
            ], 
            [
              20.296, 
              49.745
            ], 
            [
              20.338, 
              49.745
            ], 
            [
              20.338, 
              49.698
            ], 
            [
              20.296, 
              49.698
            ]
          ]
        ]
      }, 
      "type": "Feature", 
      "properties": {
        "lang": "POL", 
        "woeid": 523341, 
        "name": "Tymbark", 
        "adjacent_woeid": [
          491746, 
          497677, 
          504665, 
          518730, 
          527788, 
          528147, 
          24939777
        ], 
        "ne_latitude": 49.745, 
        "provider": "geoplanet 7.6.0", 
        "ne_longitude": 20.338, 
        "longitude": 20.310, 
        "placetype": "Town", 
        "iso": "PL", 
        "date_indexed": "2010-12-02T12:12:15Z", 
        "parent_woeid": 12618798, 
        "latitude": 49.735, 
        "sw_longitude": 20.296, 
        "fullname": "Tymbark, Lesser Poland, Limanowa County, Poland", 
        "sw_latitude": 49.698
      }, 
      "id": 523341
    }
  ]
}