{
  "type": "FeatureCollection", 
  "features": [
    {
      "geometry": {
        "type": "Polygon", 
        "coordinates": [
          [
            [
              87.640, 
              21.700
            ], 
            [
              87.640, 
              21.718
            ], 
            [
              87.660, 
              21.718
            ], 
            [
              87.660, 
              21.700
            ], 
            [
              87.640, 
              21.700
            ]
          ]
        ]
      }, 
      "type": "Feature", 
      "properties": {
        "lang": "ENG", 
        "woeid": 29014750, 
        "name": "Ghol", 
        "adjacent_woeid": [
          29014734, 
          29014736, 
          29014737, 
          29014741, 
          29014749, 
          29014751, 
          29014752
        ], 
        "ne_latitude": 21.718, 
        "provider": "geoplanet 7.6.0", 
        "ne_longitude": 87.660, 
        "longitude": 87.650, 
        "placetype": "Town", 
        "iso": "IN", 
        "date_indexed": "2010-12-02T09:01:11Z", 
        "parent_woeid": 12586805, 
        "latitude": 21.709, 
        "sw_longitude": 87.640, 
        "fullname": "Ghol, West Bengal, Midnapur, India", 
        "sw_latitude": 21.700
      }, 
      "id": 29014750
    }
  ]
}