{
  "type": "FeatureCollection", 
  "features": [
    {
      "geometry": {
        "type": "Polygon", 
        "coordinates": [
          [
            [
              84.706, 
              24.637
            ], 
            [
              84.706, 
              24.655
            ], 
            [
              84.726, 
              24.655
            ], 
            [
              84.726, 
              24.637
            ], 
            [
              84.706, 
              24.637
            ]
          ]
        ]
      }, 
      "type": "Feature", 
      "properties": {
        "lang": "ENG", 
        "woeid": 29174430, 
        "name": "Pakri", 
        "adjacent_woeid": [
          29174427, 
          29174428, 
          29174429, 
          29174431, 
          29174432, 
          29174449
        ], 
        "ne_latitude": 24.655, 
        "provider": "geoplanet 7.6.0", 
        "ne_longitude": 84.726, 
        "longitude": 84.716, 
        "placetype": "Town", 
        "iso": "IN", 
        "date_indexed": "2010-12-02T09:15:01Z", 
        "parent_woeid": 12586381, 
        "latitude": 24.646, 
        "sw_longitude": 84.706, 
        "fullname": "Pakri, Bihar, Gaya, India", 
        "sw_latitude": 24.637
      }, 
      "id": 29174430
    }
  ]
}