{
  "type": "FeatureCollection", 
  "features": [
    {
      "geometry": {
        "type": "Polygon", 
        "coordinates": [
          [
            [
              6.427, 
              50.878
            ], 
            [
              6.427, 
              50.887
            ], 
            [
              6.441, 
              50.887
            ], 
            [
              6.441, 
              50.878
            ], 
            [
              6.427, 
              50.878
            ]
          ]
        ]
      }, 
      "type": "Feature", 
      "properties": {
        "lang": "GER", 
        "woeid": 20169090, 
        "name": "Haus Eilen", 
        "ne_latitude": 50.887, 
        "provider": "geoplanet 7.6.0", 
        "ne_longitude": 6.441, 
        "longitude": 6.434, 
        "placetype": "Town", 
        "iso": "DE", 
        "date_indexed": "2010-12-02T09:40:02Z", 
        "parent_woeid": 12624621, 
        "latitude": 50.883, 
        "sw_longitude": 6.427, 
        "fullname": "Haus Eilen, North Rhine-Westphalia, Landkreis D\u00fcren, Germany", 
        "sw_latitude": 50.878
      }, 
      "id": 20169090
    }
  ]
}