{
  "type": "FeatureCollection", 
  "features": [
    {
      "geometry": {
        "type": "Polygon", 
        "coordinates": [
          [
            [
              20.402, 
              38.204
            ], 
            [
              20.402, 
              38.222
            ], 
            [
              20.426, 
              38.222
            ], 
            [
              20.426, 
              38.204
            ], 
            [
              20.402, 
              38.204
            ]
          ]
        ]
      }, 
      "type": "Feature", 
      "properties": {
        "lang": "UNK", 
        "woeid": 56023267, 
        "name": "Agios Vasileios", 
        "adjacent_woeid": [
          946975, 
          950457
        ], 
        "ne_latitude": 38.222, 
        "provider": "geoplanet 7.6.0", 
        "ne_longitude": 20.426, 
        "longitude": 20.414, 
        "placetype": "Town", 
        "iso": "GR", 
        "date_indexed": "2010-12-02T16:51:58Z", 
        "parent_woeid": 24544088, 
        "latitude": 38.213, 
        "sw_longitude": 20.402, 
        "fullname": "Agios Vasileios, Nisia Ionioy, Kefallinia, Greece", 
        "sw_latitude": 38.204
      }, 
      "id": 56023267
    }
  ]
}