{
  "type": "FeatureCollection", 
  "features": [
    {
      "geometry": {
        "type": "Polygon", 
        "coordinates": [
          [
            [
              -110.130, 
              35.776
            ], 
            [
              -110.130, 
              35.785
            ], 
            [
              -110.119, 
              35.785
            ], 
            [
              -110.119, 
              35.776
            ], 
            [
              -110.130, 
              35.776
            ]
          ]
        ]
      }, 
      "type": "Feature", 
      "properties": {
        "lang": "ENG", 
        "woeid": 2433745, 
        "name": "Kokopnyama", 
        "ne_latitude": 35.785, 
        "provider": "geoplanet 7.6.0", 
        "ne_longitude": -110.119, 
        "longitude": -110.125, 
        "placetype": "Town", 
        "iso": "US", 
        "date_indexed": "2010-12-02T18:27:50Z", 
        "parent_woeid": 12587589, 
        "latitude": 35.780, 
        "sw_longitude": -110.130, 
        "fullname": "Kokopnyama, Arizona, Navajo, United States", 
        "sw_latitude": 35.776
      }, 
      "id": 2433745
    }
  ]
}