{
  "type": "FeatureCollection", 
  "features": [
    {
      "geometry": {
        "type": "Polygon", 
        "coordinates": [
          [
            [
              3.029, 
              45.326
            ], 
            [
              3.029, 
              45.335
            ], 
            [
              3.042, 
              45.335
            ], 
            [
              3.042, 
              45.326
            ], 
            [
              3.029, 
              45.326
            ]
          ]
        ]
      }, 
      "type": "Feature", 
      "properties": {
        "lang": "FRE", 
        "woeid": 20207494, 
        "name": "La Combes", 
        "ne_latitude": 45.335, 
        "provider": "geoplanet 7.6.0", 
        "ne_longitude": 3.042, 
        "longitude": 3.036, 
        "placetype": "Town", 
        "iso": "FR", 
        "date_indexed": "2010-12-02T11:57:50Z", 
        "parent_woeid": 12637204, 
        "latitude": 45.331, 
        "sw_longitude": 3.029, 
        "fullname": "La Combes, Auvergne, Puy-de-Dome, France", 
        "sw_latitude": 45.326
      }, 
      "id": 20207494
    }
  ]
}