{
  "type": "FeatureCollection", 
  "features": [
    {
      "geometry": {
        "type": "Polygon", 
        "coordinates": [
          [
            [
              16.568, 
              48.005
            ], 
            [
              16.568, 
              48.024
            ], 
            [
              16.595, 
              48.024
            ], 
            [
              16.595, 
              48.005
            ], 
            [
              16.568, 
              48.005
            ]
          ]
        ]
      }, 
      "type": "Feature", 
      "properties": {
        "lang": "GER", 
        "woeid": 541795, 
        "name": "G\u00f6tzendorf", 
        "alias_ENG_P": [
          "Goetzendorf"
        ], 
        "alias_GER_S": [
          "Goetzendorf an der Leitha"
        ], 
        "ne_latitude": 48.024, 
        "provider": "geoplanet 7.6.0", 
        "ne_longitude": 16.595, 
        "longitude": 16.581, 
        "placetype": "Town", 
        "adjacent_woeid": [
          541431, 
          541817, 
          542726, 
          542740, 
          543304, 
          543865, 
          544073, 
          20094523, 
          20096600, 
          20097198, 
          28995541, 
          28995692
        ], 
        "iso": "AT", 
        "date_indexed": "2010-12-02T16:34:25Z", 
        "parent_woeid": 12674021, 
        "latitude": 48.015, 
        "sw_longitude": 16.568, 
        "fullname": "G\u00f6tzendorf, Goetzendorf, Lower Austria, Bruck an der Leitha, Austria", 
        "alias_GER_V": [
          "G\u00f6tzendorf an der Leitha"
        ], 
        "sw_latitude": 48.005
      }, 
      "id": 541795
    }
  ]
}