{
  "type": "FeatureCollection", 
  "features": [
    {
      "geometry": {
        "type": "Polygon", 
        "coordinates": [
          [
            [
              74.089, 
              21.815
            ], 
            [
              74.089, 
              21.833
            ], 
            [
              74.109, 
              21.833
            ], 
            [
              74.109, 
              21.815
            ], 
            [
              74.089, 
              21.815
            ]
          ]
        ]
      }, 
      "type": "Feature", 
      "properties": {
        "lang": "ENG", 
        "woeid": 29030309, 
        "name": "Katri", 
        "adjacent_woeid": [
          2279716, 
          29030263, 
          29030272, 
          29030310, 
          29030311, 
          29188003, 
          29188004
        ], 
        "ne_latitude": 21.833, 
        "provider": "geoplanet 7.6.0", 
        "ne_longitude": 74.109, 
        "longitude": 74.103, 
        "placetype": "Town", 
        "iso": "IN", 
        "date_indexed": "2010-12-02T09:24:46Z", 
        "parent_woeid": 28298858, 
        "latitude": 21.822, 
        "sw_longitude": 74.089, 
        "fullname": "Katri, Maharashtra, Nandurbar, India", 
        "sw_latitude": 21.815
      }, 
      "id": 29030309
    }
  ]
}