{
  "type": "FeatureCollection", 
  "features": [
    {
      "geometry": {
        "type": "Polygon", 
        "coordinates": [
          [
            [
              -75.168, 
              39.678
            ], 
            [
              -75.168, 
              39.738
            ], 
            [
              -75.055, 
              39.738
            ], 
            [
              -75.055, 
              39.678
            ], 
            [
              -75.168, 
              39.678
            ]
          ]
        ]
      }, 
      "type": "Feature", 
      "properties": {
        "lang": "ENG", 
        "woeid": 2410649, 
        "name": "Glassboro", 
        "adjacent_woeid": [
          2357431, 
          2381087, 
          2387554, 
          2398957, 
          2400987, 
          2407051, 
          2453066, 
          2456254, 
          2473163, 
          2481014, 
          2491111, 
          2520917, 
          28339595, 
          28745332, 
          28745393, 
          28745538
        ], 
        "ne_latitude": 39.738, 
        "provider": "geoplanet 7.6.0", 
        "ne_longitude": -75.055, 
        "longitude": -75.111, 
        "placetype": "Town", 
        "iso": "US", 
        "date_indexed": "2010-12-02T18:37:11Z", 
        "parent_woeid": 12589265, 
        "latitude": 39.707, 
        "sw_longitude": -75.168, 
        "fullname": "Glassboro, New Jersey, Gloucester, United States", 
        "sw_latitude": 39.678
      }, 
      "id": 2410649
    }
  ]
}