{
  "type": "FeatureCollection", 
  "features": [
    {
      "type": "Feature", 
      "properties": {
        "lang": "ENG", 
        "adjacent_woeid": [
          2116870, 
          2120781, 
          2090860, 
          2051419, 
          2072478, 
          2101058
        ], 
        "name": "KRASNOE", 
        "parent_woeid": 12598687, 
        "provider": "geoplanet 7.6.0", 
        "placetype": "Town", 
        "iso": "RU", 
        "woeid": 2029078, 
        "date_indexed": "2010-12-02T16:10:33Z"
      }, 
      "id": 2029078
    }
  ]
}