{
  "type": "FeatureCollection", 
  "features": [
    {
      "geometry": {
        "type": "Polygon", 
        "coordinates": [
          [
            [
              -109.210, 
              28.958
            ], 
            [
              -109.210, 
              28.976
            ], 
            [
              -109.190, 
              28.976
            ], 
            [
              -109.190, 
              28.958
            ], 
            [
              -109.210, 
              28.958
            ]
          ]
        ]
      }, 
      "type": "Feature", 
      "properties": {
        "lang": "SPA", 
        "ne_latitude": 28.976, 
        "name": "Santo Tom\u00e1s", 
        "adjacent_woeid": [
          112384, 
          112865, 
          124551, 
          137092, 
          141122, 
          147495
        ], 
        "woeid": 147257, 
        "alias_SPA_V": [
          "Sto. Tom\u00e1s"
        ], 
        "ne_longitude": -109.190, 
        "longitude": -109.200, 
        "parent_woeid": 12601597, 
        "placetype": "Town", 
        "alias_SPA_S": [
          "Sto. Tomas"
        ], 
        "iso": "MX", 
        "date_indexed": "2010-12-02T16:56:57Z", 
        "provider": "geoplanet 7.6.0", 
        "latitude": 28.967, 
        "sw_longitude": -109.210, 
        "fullname": "Santo Tom\u00e1s, Sonora, Sahuaripa, Mexico", 
        "sw_latitude": 28.958
      }, 
      "id": 147257
    }
  ]
}