{
  "type": "FeatureCollection", 
  "features": [
    {
      "geometry": {
        "type": "Polygon", 
        "coordinates": [
          [
            [
              2.893, 
              46.845
            ], 
            [
              2.893, 
              46.855
            ], 
            [
              2.907, 
              46.855
            ], 
            [
              2.907, 
              46.845
            ], 
            [
              2.893, 
              46.845
            ]
          ]
        ]
      }, 
      "type": "Feature", 
      "properties": {
        "lang": "FRE", 
        "woeid": 578868, 
        "name": "Beauvais", 
        "ne_latitude": 46.855, 
        "provider": "geoplanet 7.6.0", 
        "ne_longitude": 2.907, 
        "longitude": 2.900, 
        "placetype": "Town", 
        "iso": "FR", 
        "date_indexed": "2010-12-02T11:56:21Z", 
        "parent_woeid": 12638454, 
        "latitude": 46.850, 
        "sw_longitude": 2.893, 
        "fullname": "Beauvais, Centre, Cher, France", 
        "sw_latitude": 46.845
      }, 
      "id": 578868
    }
  ]
}