{
  "type": "FeatureCollection", 
  "features": [
    {
      "geometry": {
        "type": "Polygon", 
        "coordinates": [
          [
            [
              77.969, 
              26.764
            ], 
            [
              77.969, 
              26.782
            ], 
            [
              77.989, 
              26.782
            ], 
            [
              77.989, 
              26.764
            ], 
            [
              77.969, 
              26.764
            ]
          ]
        ]
      }, 
      "type": "Feature", 
      "properties": {
        "lang": "ENG", 
        "woeid": 29065072, 
        "name": "Bareh Mori", 
        "adjacent_woeid": [
          29065053, 
          29065054, 
          29065071, 
          29065073
        ], 
        "ne_latitude": 26.782, 
        "provider": "geoplanet 7.6.0", 
        "ne_longitude": 77.989, 
        "longitude": 77.979, 
        "placetype": "Town", 
        "iso": "IN", 
        "date_indexed": "2010-12-02T09:05:34Z", 
        "parent_woeid": 12586658, 
        "latitude": 26.773, 
        "sw_longitude": 77.969, 
        "fullname": "Bareh Mori, Rajasthan, Dhaulpur, India", 
        "sw_latitude": 26.764
      }, 
      "id": 29065072
    }
  ]
}