{
  "type": "FeatureCollection", 
  "features": [
    {
      "geometry": {
        "type": "Polygon", 
        "coordinates": [
          [
            [
              -81.293, 
              40.774
            ], 
            [
              -81.293, 
              40.792
            ], 
            [
              -81.268, 
              40.792
            ], 
            [
              -81.268, 
              40.774
            ], 
            [
              -81.293, 
              40.774
            ]
          ]
        ]
      }, 
      "type": "Feature", 
      "properties": {
        "lang": "ENG", 
        "woeid": 28339847, 
        "name": "Osnaburg", 
        "adjacent_woeid": [
          2361621, 
          2445349
        ], 
        "ne_latitude": 40.792, 
        "provider": "geoplanet 7.6.0", 
        "ne_longitude": -81.268, 
        "longitude": -81.281, 
        "placetype": "Town", 
        "iso": "US", 
        "date_indexed": "2010-12-02T18:34:16Z", 
        "parent_woeid": 12589602, 
        "latitude": 40.783, 
        "sw_longitude": -81.293, 
        "fullname": "Osnaburg, Ohio, Stark, United States", 
        "sw_latitude": 40.774
      }, 
      "id": 28339847
    }
  ]
}