{
  "type": "FeatureCollection", 
  "features": [
    {
      "geometry": {
        "type": "Polygon", 
        "coordinates": [
          [
            [
              82.844, 
              18.895
            ], 
            [
              82.844, 
              18.913
            ], 
            [
              82.863, 
              18.913
            ], 
            [
              82.863, 
              18.895
            ], 
            [
              82.844, 
              18.895
            ]
          ]
        ]
      }, 
      "type": "Feature", 
      "properties": {
        "lang": "ENG", 
        "woeid": 29056610, 
        "name": "Tamili", 
        "adjacent_woeid": [
          29056581, 
          29056604, 
          29056606, 
          29056609, 
          29056613, 
          29056614, 
          29056615
        ], 
        "ne_latitude": 18.913, 
        "provider": "geoplanet 7.6.0", 
        "ne_longitude": 82.863, 
        "longitude": 82.853, 
        "placetype": "Town", 
        "iso": "IN", 
        "date_indexed": "2010-12-02T09:04:33Z", 
        "parent_woeid": 12586616, 
        "latitude": 18.904, 
        "sw_longitude": 82.844, 
        "fullname": "Tamili, Orissa, Koraput, India", 
        "sw_latitude": 18.895
      }, 
      "id": 29056610
    }
  ]
}