{
  "type": "FeatureCollection", 
  "features": [
    {
      "geometry": {
        "type": "Polygon", 
        "coordinates": [
          [
            [
              84.596, 
              25.031
            ], 
            [
              84.596, 
              25.050
            ], 
            [
              84.616, 
              25.050
            ], 
            [
              84.616, 
              25.031
            ], 
            [
              84.596, 
              25.031
            ]
          ]
        ]
      }, 
      "type": "Feature", 
      "properties": {
        "lang": "ENG", 
        "woeid": 29173460, 
        "name": "Jakhaura", 
        "adjacent_woeid": [
          29173427, 
          29173428, 
          29173459, 
          29173461, 
          29173496, 
          29173499
        ], 
        "ne_latitude": 25.050, 
        "provider": "geoplanet 7.6.0", 
        "ne_longitude": 84.616, 
        "longitude": 84.606, 
        "placetype": "Town", 
        "iso": "IN", 
        "date_indexed": "2010-12-02T09:14:55Z", 
        "parent_woeid": 12586374, 
        "latitude": 25.041, 
        "sw_longitude": 84.596, 
        "fullname": "Jakhaura, Bihar, Aurangabad, India", 
        "sw_latitude": 25.031
      }, 
      "id": 29173460
    }
  ]
}