{
  "type": "FeatureCollection", 
  "features": [
    {
      "geometry": {
        "type": "Polygon", 
        "coordinates": [
          [
            [
              -5.894, 
              36.500
            ], 
            [
              -5.894, 
              36.541
            ], 
            [
              -5.829, 
              36.541
            ], 
            [
              -5.829, 
              36.500
            ], 
            [
              -5.894, 
              36.500
            ]
          ]
        ]
      }, 
      "type": "Feature", 
      "properties": {
        "lang": "SPA", 
        "ne_latitude": 36.541, 
        "name": "Paterna de Rivera", 
        "adjacent_woeid": [
          751772, 
          753592, 
          762833, 
          766962, 
          779219, 
          20228923
        ], 
        "woeid": 769582, 
        "alias_SPA_V": [
          "Paterna de la Rivera"
        ], 
        "ne_longitude": -5.829, 
        "longitude": -5.867, 
        "parent_woeid": 12688752, 
        "placetype": "Town", 
        "iso": "ES", 
        "date_indexed": "2010-12-02T17:11:09Z", 
        "provider": "geoplanet 7.6.0", 
        "latitude": 36.526, 
        "sw_longitude": -5.894, 
        "fullname": "Paterna de Rivera, Andalusia, Cadiz, Spain", 
        "sw_latitude": 36.500
      }, 
      "id": 769582
    }
  ]
}