{
  "type": "FeatureCollection", 
  "features": [
    {
      "type": "Feature", 
      "properties": {
        "lang": "ENG", 
        "alias_ENG_V": [
          "Sisian"
        ], 
        "name": "Hats'avan", 
        "adjacent_woeid": [
          2213610, 
          2213639, 
          2213464, 
          2214412, 
          2214609, 
          2213431
        ], 
        "parent_woeid": 15022549, 
        "provider": "geoplanet 7.6.0", 
        "placetype": "Town", 
        "iso": "AM", 
        "woeid": 2213838, 
        "date_indexed": "2010-12-02T12:16:10Z"
      }, 
      "id": 2213838
    }
  ]
}