{
  "type": "FeatureCollection", 
  "features": [
    {
      "geometry": {
        "type": "Polygon", 
        "coordinates": [
          [
            [
              -83.448, 
              38.311
            ], 
            [
              -83.448, 
              38.320
            ], 
            [
              -83.437, 
              38.320
            ], 
            [
              -83.437, 
              38.311
            ], 
            [
              -83.448, 
              38.311
            ]
          ]
        ]
      }, 
      "type": "Feature", 
      "properties": {
        "lang": "ENG", 
        "woeid": 2514029, 
        "name": "Waltz", 
        "adjacent_woeid": [
          2386725, 
          2387890, 
          2421734, 
          2474360, 
          2494832, 
          2508060
        ], 
        "ne_latitude": 38.320, 
        "provider": "geoplanet 7.6.0", 
        "ne_longitude": -83.437, 
        "longitude": -83.443, 
        "placetype": "Town", 
        "iso": "US", 
        "date_indexed": "2010-12-02T18:33:04Z", 
        "parent_woeid": 12588578, 
        "latitude": 38.315, 
        "sw_longitude": -83.448, 
        "fullname": "Waltz, Kentucky, Rowan, United States", 
        "sw_latitude": 38.311
      }, 
      "id": 2514029
    }
  ]
}