{
  "type": "FeatureCollection", 
  "features": [
    {
      "geometry": {
        "type": "Polygon", 
        "coordinates": [
          [
            [
              -2.274, 
              42.860
            ], 
            [
              -2.274, 
              42.907
            ], 
            [
              -2.246, 
              42.907
            ], 
            [
              -2.246, 
              42.860
            ], 
            [
              -2.274, 
              42.860
            ]
          ]
        ]
      }, 
      "type": "Feature", 
      "properties": {
        "lang": "SPA", 
        "ne_latitude": 42.907, 
        "name": "Eguino", 
        "adjacent_woeid": [
          752452, 
          757652, 
          762489, 
          762562, 
          20225054
        ], 
        "woeid": 758896, 
        "alias_SPA_V": [
          "Egino"
        ], 
        "ne_longitude": -2.246, 
        "longitude": -2.265, 
        "parent_woeid": 12695023, 
        "placetype": "Town", 
        "iso": "ES", 
        "date_indexed": "2010-12-02T17:09:41Z", 
        "provider": "geoplanet 7.6.0", 
        "latitude": 42.870, 
        "sw_longitude": -2.274, 
        "fullname": "Eguino, Basque Country, Alava, Spain", 
        "sw_latitude": 42.860
      }, 
      "id": 758896
    }
  ]
}