{
  "type": "FeatureCollection", 
  "features": [
    {
      "geometry": {
        "type": "Polygon", 
        "coordinates": [
          [
            [
              15.063, 
              49.287
            ], 
            [
              15.063, 
              49.314
            ], 
            [
              15.093, 
              49.314
            ], 
            [
              15.093, 
              49.287
            ], 
            [
              15.063, 
              49.287
            ]
          ]
        ]
      }, 
      "type": "Feature", 
      "properties": {
        "lang": "CZE", 
        "woeid": 791024, 
        "name": "Kamenice nad Lipou", 
        "adjacent_woeid": [
          785856, 
          786628, 
          787208, 
          787382, 
          787730, 
          789098, 
          789691, 
          790912, 
          791097, 
          794108, 
          794845, 
          794913, 
          799590, 
          802139, 
          24930609, 
          24930670
        ], 
        "ne_latitude": 49.314, 
        "provider": "geoplanet 7.6.0", 
        "ne_longitude": 15.093, 
        "longitude": 15.077, 
        "placetype": "Town", 
        "alias_CZE_V": [
          "Kamenitz an der Linde"
        ], 
        "iso": "CZ", 
        "date_indexed": "2010-12-02T08:55:57Z", 
        "parent_woeid": 12604378, 
        "latitude": 49.303, 
        "sw_longitude": 15.063, 
        "fullname": "Kamenice nad Lipou, Vyso\u010dina, Pelh\u0159imov, Czech Republic", 
        "sw_latitude": 49.287
      }, 
      "id": 791024
    }
  ]
}