{
  "type": "FeatureCollection", 
  "features": [
    {
      "geometry": {
        "type": "Polygon", 
        "coordinates": [
          [
            [
              18.071, 
              40.507
            ], 
            [
              18.071, 
              40.525
            ], 
            [
              18.096, 
              40.525
            ], 
            [
              18.096, 
              40.507
            ], 
            [
              18.071, 
              40.507
            ]
          ]
        ]
      }, 
      "type": "Feature", 
      "properties": {
        "lang": "ITA", 
        "woeid": 29340409, 
        "name": "Lindinuso", 
        "adjacent_woeid": [
          712771, 
          724996, 
          29340408
        ], 
        "ne_latitude": 40.525, 
        "provider": "geoplanet 7.6.0", 
        "ne_longitude": 18.096, 
        "longitude": 18.083, 
        "placetype": "Town", 
        "iso": "IT", 
        "date_indexed": "2010-12-02T16:30:21Z", 
        "parent_woeid": 12679916, 
        "latitude": 40.516, 
        "sw_longitude": 18.071, 
        "fullname": "Lindinuso, Puglia, Brindisi, Italy", 
        "sw_latitude": 40.507
      }, 
      "id": 29340409
    }
  ]
}