{
  "type": "FeatureCollection", 
  "features": [
    {
      "geometry": {
        "type": "Polygon", 
        "coordinates": [
          [
            [
              16.288, 
              47.320
            ], 
            [
              16.288, 
              47.338
            ], 
            [
              16.315, 
              47.338
            ], 
            [
              16.315, 
              47.320
            ], 
            [
              16.288, 
              47.320
            ]
          ]
        ]
      }, 
      "type": "Feature", 
      "properties": {
        "lang": "GER", 
        "woeid": 539011, 
        "name": "Rauhriegel", 
        "adjacent_woeid": [
          538947, 
          539046
        ], 
        "ne_latitude": 47.338, 
        "provider": "geoplanet 7.6.0", 
        "ne_longitude": 16.315, 
        "longitude": 16.301, 
        "placetype": "Town", 
        "iso": "AT", 
        "date_indexed": "2010-12-02T16:34:17Z", 
        "parent_woeid": 12673376, 
        "latitude": 47.329, 
        "sw_longitude": 16.288, 
        "fullname": "Rauhriegel, Burgenland, Oberwart, Austria", 
        "sw_latitude": 47.320
      }, 
      "id": 539011
    }
  ]
}