{
  "type": "FeatureCollection", 
  "features": [
    {
      "type": "Feature", 
      "properties": {
        "lang": "ENG", 
        "adjacent_woeid": [
          1061854, 
          1061819, 
          1062160, 
          1061833, 
          1061855, 
          1062153, 
          1061839, 
          1061824, 
          1061816
        ], 
        "name": "Uraru", 
        "parent_woeid": 2346582, 
        "provider": "geoplanet 7.6.0", 
        "placetype": "Town", 
        "iso": "PG", 
        "woeid": 1061836, 
        "date_indexed": "2010-12-02T09:57:22Z"
      }, 
      "id": 1061836
    }
  ]
}