{
  "type": "FeatureCollection", 
  "features": [
    {
      "geometry": {
        "type": "Polygon", 
        "coordinates": [
          [
            [
              -84.922, 
              45.632
            ], 
            [
              -84.922, 
              45.641
            ], 
            [
              -84.909, 
              45.641
            ], 
            [
              -84.909, 
              45.632
            ], 
            [
              -84.922, 
              45.632
            ]
          ]
        ]
      }, 
      "type": "Feature", 
      "properties": {
        "lang": "ENG", 
        "woeid": 2374220, 
        "name": "Canby Corners", 
        "alias_ENG_V": [
          "Canby Cors"
        ], 
        "ne_latitude": 45.641, 
        "provider": "geoplanet 7.6.0", 
        "ne_longitude": -84.909, 
        "longitude": -84.915, 
        "placetype": "Town", 
        "iso": "US", 
        "date_indexed": "2010-12-02T18:23:29Z", 
        "parent_woeid": 12588737, 
        "latitude": 45.636, 
        "sw_longitude": -84.922, 
        "fullname": "Canby Corners, Michigan, Emmet, United States", 
        "sw_latitude": 45.632
      }, 
      "id": 2374220
    }
  ]
}