{
  "type": "FeatureCollection", 
  "features": [
    {
      "type": "Feature", 
      "properties": {
        "lang": "POL", 
        "adjacent_woeid": [
          492310, 
          509799, 
          24934187, 
          24942537, 
          24934252, 
          528035, 
          513360, 
          490547, 
          488412
        ], 
        "name": "Teremiski", 
        "parent_woeid": 12617518, 
        "provider": "geoplanet 7.6.0", 
        "placetype": "Town", 
        "iso": "PL", 
        "woeid": 24942813, 
        "date_indexed": "2010-12-02T12:10:35Z"
      }, 
      "id": 24942813
    }
  ]
}