{
  "type": "FeatureCollection", 
  "features": [
    {
      "geometry": {
        "type": "Polygon", 
        "coordinates": [
          [
            [
              1.819, 
              46.819
            ], 
            [
              1.819, 
              46.839
            ], 
            [
              1.840, 
              46.839
            ], 
            [
              1.840, 
              46.819
            ], 
            [
              1.819, 
              46.819
            ]
          ]
        ]
      }, 
      "type": "Feature", 
      "properties": {
        "lang": "FRE", 
        "woeid": 588792, 
        "name": "Diors", 
        "adjacent_woeid": [
          610183, 
          614240, 
          627516, 
          20185806
        ], 
        "ne_latitude": 46.839, 
        "provider": "geoplanet 7.6.0", 
        "ne_longitude": 1.840, 
        "longitude": 1.828, 
        "placetype": "Town", 
        "iso": "FR", 
        "date_indexed": "2010-12-02T12:02:51Z", 
        "parent_woeid": 12642949, 
        "latitude": 46.827, 
        "sw_longitude": 1.819, 
        "fullname": "Diors, Centre, Indre, France", 
        "sw_latitude": 46.819
      }, 
      "id": 588792
    }
  ]
}